README.md
setup.py
dj_pysher/__init__.py
dj_pysher/application.py
dj_pysher/apps.py
dj_pysher/sender.py
dj_pysher/tools.py
dj_pysher.egg-info/PKG-INFO
dj_pysher.egg-info/SOURCES.txt
dj_pysher.egg-info/dependency_links.txt
dj_pysher.egg-info/requires.txt
dj_pysher.egg-info/top_level.txt
dj_pysher/management/__init__.py
dj_pysher/management/commands/__init__.py
dj_pysher/management/commands/pusher_client.py